{
  "version": "1.0",
  "defaultProvider": "jsdelivr",
  "libraries": [
    {
      "library": "mediasoup-client@3.6.34",
      "destination": "wwwroot/lib/mediasoup-client/",
      "files": [
        ".eslintrc.js",
        ".eslintrc.min.js",
        ".travis.yml",
        ".vimrc",
        "LICENSE",
        "npm-scripts.js",
        "npm-scripts.min.js",
        "package.json",
        "README.md",
        "tsconfig.json",
        "lib/Consumer.d.ts",
        "lib/Consumer.d.ts.map",
        "lib/Consumer.js",
        "lib/Consumer.min.js",
        "lib/DataConsumer.d.ts",
        "lib/DataConsumer.d.ts.map",
        "lib/DataConsumer.js",
        "lib/DataConsumer.min.js",
        "lib/DataProducer.d.ts",
        "lib/DataProducer.d.ts.map",
        "lib/DataProducer.js",
        "lib/DataProducer.min.js",
        "lib/Device.d.ts",
        "lib/Device.d.ts.map",
        "lib/Device.js",
        "lib/Device.min.js",
        "lib/EnhancedEventEmitter.d.ts",
        "lib/EnhancedEventEmitter.d.ts.map",
        "lib/EnhancedEventEmitter.js",
        "lib/EnhancedEventEmitter.min.js",
        "lib/errors.d.ts",
        "lib/errors.d.ts.map",
        "lib/errors.js",
        "lib/errors.min.js",
        "lib/index.d.ts",
        "lib/index.d.ts.map",
        "lib/index.js",
        "lib/index.min.js",
        "lib/Logger.d.ts",
        "lib/Logger.d.ts.map",
        "lib/Logger.js",
        "lib/Logger.min.js",
        "lib/ortc.d.ts",
        "lib/ortc.d.ts.map",
        "lib/ortc.js",
        "lib/ortc.min.js",
        "lib/Producer.d.ts",
        "lib/Producer.d.ts.map",
        "lib/Producer.js",
        "lib/Producer.min.js",
        "lib/RtpParameters.d.ts",
        "lib/RtpParameters.d.ts.map",
        "lib/RtpParameters.js",
        "lib/RtpParameters.min.js",
        "lib/scalabilityModes.d.ts",
        "lib/scalabilityModes.d.ts.map",
        "lib/scalabilityModes.js",
        "lib/scalabilityModes.min.js",
        "lib/SctpParameters.d.ts",
        "lib/SctpParameters.d.ts.map",
        "lib/SctpParameters.js",
        "lib/SctpParameters.min.js",
        "lib/Transport.d.ts",
        "lib/Transport.d.ts.map",
        "lib/Transport.js",
        "lib/Transport.min.js",
        "lib/types.d.ts",
        "lib/types.d.ts.map",
        "lib/types.js",
        "lib/types.min.js",
        "lib/utils.d.ts",
        "lib/utils.d.ts.map",
        "lib/utils.js",
        "lib/utils.min.js",
        "lib/handlers/ortc/edgeUtils.d.ts",
        "lib/handlers/ortc/edgeUtils.d.ts.map",
        "lib/handlers/ortc/edgeUtils.js",
        "lib/handlers/ortc/edgeUtils.min.js",
        "lib/handlers/sdp/commonUtils.d.ts",
        "lib/handlers/sdp/commonUtils.d.ts.map",
        "lib/handlers/sdp/commonUtils.js",
        "lib/handlers/sdp/commonUtils.min.js",
        "lib/handlers/sdp/MediaSection.d.ts",
        "lib/handlers/sdp/MediaSection.d.ts.map",
        "lib/handlers/sdp/MediaSection.js",
        "lib/handlers/sdp/MediaSection.min.js",
        "lib/handlers/sdp/plainRtpUtils.d.ts",
        "lib/handlers/sdp/plainRtpUtils.d.ts.map",
        "lib/handlers/sdp/plainRtpUtils.js",
        "lib/handlers/sdp/plainRtpUtils.min.js",
        "lib/handlers/sdp/planBUtils.d.ts",
        "lib/handlers/sdp/planBUtils.d.ts.map",
        "lib/handlers/sdp/planBUtils.js",
        "lib/handlers/sdp/planBUtils.min.js",
        "lib/handlers/sdp/RemoteSdp.d.ts",
        "lib/handlers/sdp/RemoteSdp.d.ts.map",
        "lib/handlers/sdp/RemoteSdp.js",
        "lib/handlers/sdp/RemoteSdp.min.js",
        "lib/handlers/sdp/unifiedPlanUtils.d.ts",
        "lib/handlers/sdp/unifiedPlanUtils.d.ts.map",
        "lib/handlers/sdp/unifiedPlanUtils.js",
        "lib/handlers/sdp/unifiedPlanUtils.min.js",
        "lib/handlers/Chrome55.d.ts",
        "lib/handlers/Chrome55.d.ts.map",
        "lib/handlers/Chrome55.js",
        "lib/handlers/Chrome55.min.js",
        "lib/handlers/Chrome67.d.ts",
        "lib/handlers/Chrome67.d.ts.map",
        "lib/handlers/Chrome67.js",
        "lib/handlers/Chrome67.min.js",
        "lib/handlers/Chrome70.d.ts",
        "lib/handlers/Chrome70.d.ts.map",
        "lib/handlers/Chrome70.js",
        "lib/handlers/Chrome70.min.js",
        "lib/handlers/Chrome74.d.ts",
        "lib/handlers/Chrome74.d.ts.map",
        "lib/handlers/Chrome74.js",
        "lib/handlers/Chrome74.min.js",
        "lib/handlers/Edge11.d.ts",
        "lib/handlers/Edge11.d.ts.map",
        "lib/handlers/Edge11.js",
        "lib/handlers/Edge11.min.js",
        "lib/handlers/FakeHandler.d.ts",
        "lib/handlers/FakeHandler.d.ts.map",
        "lib/handlers/FakeHandler.js",
        "lib/handlers/FakeHandler.min.js",
        "lib/handlers/Firefox60.d.ts",
        "lib/handlers/Firefox60.d.ts.map",
        "lib/handlers/Firefox60.js",
        "lib/handlers/Firefox60.min.js",
        "lib/handlers/HandlerInterface.d.ts",
        "lib/handlers/HandlerInterface.d.ts.map",
        "lib/handlers/HandlerInterface.js",
        "lib/handlers/HandlerInterface.min.js",
        "lib/handlers/ReactNative.d.ts",
        "lib/handlers/ReactNative.d.ts.map",
        "lib/handlers/ReactNative.js",
        "lib/handlers/ReactNative.min.js",
        "lib/handlers/Safari11.d.ts",
        "lib/handlers/Safari11.d.ts.map",
        "lib/handlers/Safari11.js",
        "lib/handlers/Safari11.min.js",
        "lib/handlers/Safari12.d.ts",
        "lib/handlers/Safari12.d.ts.map",
        "lib/handlers/Safari12.js",
        "lib/handlers/Safari12.min.js",
        "src/Consumer.ts",
        "src/DataConsumer.ts",
        "src/DataProducer.ts",
        "src/Device.ts",
        "src/EnhancedEventEmitter.ts",
        "src/errors.ts",
        "src/index.ts",
        "src/Logger.ts",
        "src/ortc.ts",
        "src/Producer.ts",
        "src/RtpParameters.ts",
        "src/scalabilityModes.ts",
        "src/SctpParameters.ts",
        "src/Transport.ts",
        "src/types.ts",
        "src/utils.ts",
        "src/handlers/ortc/edgeUtils.ts",
        "src/handlers/sdp/commonUtils.ts",
        "src/handlers/sdp/MediaSection.ts",
        "src/handlers/sdp/plainRtpUtils.ts",
        "src/handlers/sdp/planBUtils.ts",
        "src/handlers/sdp/RemoteSdp.ts",
        "src/handlers/sdp/unifiedPlanUtils.ts",
        "src/handlers/Chrome55.ts",
        "src/handlers/Chrome67.ts",
        "src/handlers/Chrome70.ts",
        "src/handlers/Chrome74.ts",
        "src/handlers/Edge11.ts",
        "src/handlers/FakeHandler.ts",
        "src/handlers/Firefox60.ts",
        "src/handlers/HandlerInterface.ts",
        "src/handlers/ReactNative.ts",
        "src/handlers/Safari11.ts",
        "src/handlers/Safari12.ts"
      ]
    }
  ]
}